{
  "main": {
    "id": "3c9296845a05bbba",
    "type": "split",
    "children": [
      {
        "id": "4c36a9c6245a56c5",
        "type": "tabs",
        "children": [
          {
            "id": "1c91c05aa6a17218",
            "type": "leaf",
            "state": {
              "type": "graph",
              "state": {},
              "icon": "lucide-git-fork",
              "title": "关系图谱"
            }
          }
        ]
      },
      {
        "id": "0b2f3759e4c385a8",
        "type": "tabs",
        "children": [
          {
            "id": "f0e42e65036dc54a",
            "type": "leaf",
            "state": {
              "type": "graph",
              "state": {},
              "icon": "lucide-git-fork",
              "title": "关系图谱"
            }
          }
        ]
      }
    ],
    "direction": "vertical"
  },
  "left": {
    "id": "192b43a39f044588",
    "type": "split",
    "children": [
      {
        "id": "6912f7b148a03eaf",
        "type": "tabs",
        "children": [
          {
            "id": "988179822f0f58be",
            "type": "leaf",
            "state": {
              "type": "file-explorer",
              "state": {
                "sortOrder": "alphabetical",
                "autoReveal": false
              },
              "icon": "lucide-folder-closed",
              "title": "文件列表"
            }
          },
          {
            "id": "4e7f221968e63459",
            "type": "leaf",
            "state": {
              "type": "search",
              "state": {
                "query": "",
                "matchingCase": false,
                "explainSearch": false,
                "collapseAll": false,
                "extraContext": false,
                "sortOrder": "alphabetical"
              },
              "icon": "lucide-search",
              "title": "搜索"
            }
          },
          {
            "id": "8cc3b02e08461531",
            "type": "leaf",
            "state": {
              "type": "bookmarks",
              "state": {},
              "icon": "lucide-bookmark",
              "title": "书签"
            }
          }
        ]
      }
    ],
    "direction": "horizontal",
    "width": 300
  },
  "right": {
    "id": "485891d3e61236a3",
    "type": "split",
    "children": [
      {
        "id": "5d6619cf533fe3c0",
        "type": "tabs",
        "children": [
          {
            "id": "2e92c37c1087bdf8",
            "type": "leaf",
            "state": {
              "type": "backlink",
              "state": {
                "file": "欢迎.md",
                "collapseAll": false,
                "extraContext": false,
                "sortOrder": "alphabetical",
                "showSearch": false,
                "searchQuery": "",
                "backlinkCollapsed": false,
                "unlinkedCollapsed": true
              },
              "icon": "links-coming-in",
              "title": "欢迎 的反向链接列表"
            }
          },
          {
            "id": "cfede53348bb8ded",
            "type": "leaf",
            "state": {
              "type": "outgoing-link",
              "state": {
                "file": "欢迎.md",
                "linksCollapsed": false,
                "unlinkedCollapsed": true
              },
              "icon": "links-going-out",
              "title": "欢迎 的出链列表"
            }
          },
          {
            "id": "1f64fea63e766465",
            "type": "leaf",
            "state": {
              "type": "tag",
              "state": {
                "sortOrder": "frequency",
                "useHierarchy": true,
                "showSearch": false,
                "searchQuery": ""
              },
              "icon": "lucide-tags",
              "title": "标签"
            }
          },
          {
            "id": "5114d3d8cf9ae057",
            "type": "leaf",
            "state": {
              "type": "all-properties",
              "state": {
                "sortOrder": "frequency",
                "showSearch": false,
                "searchQuery": ""
              },
              "icon": "lucide-archive",
              "title": "添加笔记属性"
            }
          },
          {
            "id": "b1a0629c8afa9e3c",
            "type": "leaf",
            "state": {
              "type": "outline",
              "state": {
                "file": "欢迎.md",
                "followCursor": false,
                "showSearch": false,
                "searchQuery": ""
              },
              "icon": "lucide-list",
              "title": "欢迎 的大纲"
            }
          }
        ]
      }
    ],
    "direction": "horizontal",
    "width": 300,
    "collapsed": true
  },
  "left-ribbon": {
    "hiddenItems": {
      "switcher:打开快速切换": false,
      "graph:查看关系图谱": false,
      "canvas:新建白板": false,
      "daily-notes:打开/创建今天的日记": false,
      "templates:插入模板": false,
      "command-palette:打开命令面板": false,
      "bases:新建数据库": false
    }
  },
  "active": "988179822f0f58be",
  "lastOpenFiles": [
    "20-Knowledge/windows-powershell-app-execution-alias-1920.md",
    "20-Knowledge/研发流程/白话文档与附录分层.md",
    "20-Knowledge/研发流程",
    "20-Knowledge/development/godot-windows-powershell-app-execution-alias.md",
    "20-Knowledge/development",
    "Untitled.md",
    "20-Knowledge/godot/Godot AI MCP 正式资产导入预览要点.md",
    "20-Knowledge/godot",
    "20-Knowledge/projects/大乱斗-C8视觉合同.md",
    "20-Knowledge/projects",
    "知识库/INDEX.md",
    "知识库/20-Knowledge/需求与实施文档零决策交接.md",
    "知识库/20-Knowledge",
    "知识库",
    "20-Knowledge/codex-rules/执行失败持续学习与主动预防.md",
    "20-Knowledge/codex-rules/Imagegen错误案例持续演进.md",
    "20-Knowledge/codex-rules/Windows-WSL命令失败恢复与Skill持续迭代.md",
    "50-Sources/repo/Uber-Go语言编码规范中文版.md",
    "50-Sources/repo",
    "20-Knowledge/通用后台异步导出下载中心完整性审查.md",
    "20-Knowledge/go/Go语言大厂编码规范资料清单.md",
    "20-Knowledge/go/golang-patterns合并候选清单.md",
    "20-Knowledge/go",
    "20-Knowledge/codex-skills/函数拆分颗粒规则.md",
    "20-Knowledge/codex-skills",
    "欢迎.md",
    "30-MOCs/blog-data/设计模式-逐篇沉淀.md",
    "30-MOCs/blog-data/算法-逐篇沉淀.md",
    "30-MOCs/blog-data/服务器-逐篇沉淀.md",
    "30-MOCs/blog-data/区块链-逐篇沉淀.md",
    "30-MOCs/blog-data/中间件-逐篇沉淀.md",
    "30-MOCs/blog-data/数据库-逐篇沉淀.md",
    "30-MOCs/blog-data/后端-逐篇沉淀.md",
    "30-MOCs/blog-data/全量逐篇沉淀总览.md",
    "30-MOCs/blog-data/前端-逐篇沉淀.md",
    "30-MOCs/blog-data"
  ]
}